deppy/__init__.py
deppy/deppy.py
deppy/graph_builder.py
deppy/ignore_result.py
deppy/node.py
deppy/scope.py
deppy/blueprint/__init__.py
deppy/blueprint/blueprint.py
deppy/blueprint/components.py
deppy/blueprint/meta.py
deppy/executor/__init__.py
deppy/executor/async_executor.py
deppy/executor/executor.py
deppy/executor/hybrid_executor.py
deppy/executor/sync_executor.py
deppy/helpers/DLT.py
deppy/helpers/__init__.py
deppy/helpers/asyncclient.py
deppy/helpers/wrappers/__init__.py
deppy/helpers/wrappers/dkr.py
deppy/helpers/wrappers/stated_kwargs.py
dep_python-1.1.5.dist-info/METADATA
dep_python-1.1.5.dist-info/WHEEL
dep_python-1.1.5.dist-info/licenses/LICENSE.txt
dep_python-1.1.5.dist-info/RECORD
