Metadata-Version: 2.4
Name: dep-python
Version: 1.1.5
Summary: Deppy: A Python dependency executor that builds and executes DAGs efficiently, optimizing workflows with concurrency and flexibility. Perfect for managing complex dependent tasks effortlessly.
Project-URL: Github, https://github.com/ArneDePeuter/deppy
Project-URL: Documentation, https://github.com/ArneDePeuter/deppy/tree/master/docs
License-File: LICENSE.txt
Requires-Python: >=3.11
Requires-Dist: networkx>=3.4.2
Requires-Dist: pydot>=3.0.4
Provides-Extra: asyncclient
Requires-Dist: httpx>=0.28.1; extra == 'asyncclient'
Provides-Extra: dlt
Requires-Dist: dlt>=1.5.0; extra == 'dlt'
